DolaBot/__init__.py
DolaBot/cogs/__init__.py
DolaBot/cogs/bot_util_commands.py
DolaBot/cogs/meme_commands.py
DolaBot/cogs/sendou_commands.py
DolaBot/cogs/server_commands.py
DolaBot/cogs/slapp_commands.py
DolaBot/cogs/splatoon_commands.py
DolaBot/constants/__init__.py
DolaBot/constants/bot_constants.py
DolaBot/constants/emojis.py
DolaBot/constants/footer_phrases.py
DolaBot/entry/DolaBot.py
DolaBot/entry/__init__.py
DolaBot/entry/main.py
DolaBot/helpers/__init__.py
DolaBot/helpers/channel_logger.py
DolaBot/helpers/discord_renderer_helper.py
DolaBot/helpers/embed_helper.py
DolaBot/helpers/processed_slapp_object.py
DolaBot/helpers/supports_send.py
DolaBot/helpers/timer_decorator.py
DolaBot/helpers/weapons.py
DolaBot/translators/GameModeTranslator.py
DolaBot/translators/StageTranslator.py
DolaBot/translators/__init__.py
DolaBot_Slate-1.0.1.dist-info/LICENSE
DolaBot_Slate-1.0.1.dist-info/METADATA
DolaBot_Slate-1.0.1.dist-info/WHEEL
DolaBot_Slate-1.0.1.dist-info/top_level.txt
DolaBot_Slate-1.0.1.dist-info/RECORD
