Metadata-Version: 2.1
Name: DolaBot-Slate
Version: 1.0.1
Summary: Python Splatoon-orientated Discord Bot that can interact with SplatTag
Home-page: https://github.com/kjhf/DolaBot
Author: Slate
License: UNKNOWN
Project-URL: Bug Reports, https://github.com/kjhf/Dola/issues
Project-URL: Source, https://github.com/kjhf/Dola/
Project-URL: Discord, https://discord.gg/wZZv2Cr
Keywords: slapp,slate,splatoon,dola
Platform: UNKNOWN
Classifier: Development Status :: 3 - Alpha
Classifier: Intended Audience :: Developers
Classifier: Topic :: Software Development :: Build Tools
Classifier: Programming Language :: Python :: 3.9
Classifier: License :: OSI Approved :: MIT License
Classifier: Operating System :: OS Independent
Requires-Python: >=3.9, <4
License-File: LICENSE
